mseep_needle_mcp-1.0.1.dist-info/licenses/LICENSE
needle_mcp/__init__.py
needle_mcp/server.py
mseep_needle_mcp-1.0.1.dist-info/METADATA
mseep_needle_mcp-1.0.1.dist-info/WHEEL
mseep_needle_mcp-1.0.1.dist-info/entry_points.txt
mseep_needle_mcp-1.0.1.dist-info/top_level.txt
mseep_needle_mcp-1.0.1.dist-info/RECORD
